digits_classifications/Deep_Learning_Model.py
digits_classifications/Neural_Networks.py
digits_classifications/__init__.py
digits_classifications-0.0.1.dist-info/LICENSE
digits_classifications-0.0.1.dist-info/METADATA
digits_classifications-0.0.1.dist-info/WHEEL
digits_classifications-0.0.1.dist-info/top_level.txt
digits_classifications-0.0.1.dist-info/RECORD
