Metadata-Version: 2.1
Name: digits-classifications
Version: 0.0.1
Summary: Package with models for digits classification
Author: Milovan Kadic
Author-email: mkadic40@gmail.com
License: MIT
Classifier: Programming Language :: Python :: 3
Classifier: License :: OSI Approved :: MIT License
Classifier: Operating System :: OS Independent
Requires-Python: >=3.7
License-File: LICENSE
